{
  "date": "2026-04-28",
  "keywords": [
    {
      "id": 1,
      "term": "公地悲剧",
      "category": "经济",
      "definition": "<strong>含义：</strong>共享资源在无约束使用时趋于过度消耗的现象，是市场失灵的典型案例，需要产权界定或集体规则来防止公共资源枯竭。",
      "example": "<strong>举例：</strong>大气是最大的“公地”，各国竞相排放CO₂；碳税和碳市场正是建立排放权市场，将大气“公地”私有化/配额化，防止公地悲剧。"
    },
    {
      "id": 2,
      "term": "用氢场景",
      "category": "能源",
      "definition": "<strong>含义：</strong>氢能在不同终端的应用领域，包括交通（重卡、船舶、航空）、工业（钢铁、化工、建材）、储能（电网调峰）、建筑（供热），各场景经济性和成熟度差异显著。",
      "example": "<strong>举例：</strong>重载长途运输因充电困难是氢能最有竞争力的场景之一；钢铁行业“氢代焦”减排潜力最大；航空氢燃料在液氢技术突破后将成重要方向。"
    },
    {
      "id": 3,
      "term": "流动性",
      "category": "经济",
      "definition": "<strong>含义：</strong>资产在不影响价格的情况下迅速变现的能力；经济学上也指货币供应量的丰裕程度，影响利率和投资意愿。",
      "example": "<strong>举例：</strong>股票流动性高（随时变现）；房产流动性低（变现需数月）；氢能基础设施是极低流动性资产——一旦投建便长期锁定，因此投资前需充分论证经济性。"
    },
    {
      "id": 4,
      "term": "调峰",
      "category": "能源",
      "definition": "<strong>含义：</strong>电力系统在用电高峰期增加出力、低谷期减少出力的灵活性手段，是电网稳定运行的关键调节机制。",
      "example": "<strong>举例：</strong>夏天中午空调用电高峰，抽水蓄能电站放水发电调峰；氢储能是未来跨季节大规模调峰的重要选项。"
    },
    {
      "id": 5,
      "term": "归因理论",
      "category": "心理",
      "definition": "<strong>含义：</strong>人们对自己和他人行为原因的解释方式，分为内部归因（能力/努力）和外部归因（运气/环境），影响动机、情绪和持续行为。",
      "example": "<strong>举例：</strong>项目失败后归因于“市场太差”（外部），下次不会改变行为；归因于“我们的执行有漏洞”（内部），才有改进动力——高效学习者擅长内部归因。"
    }
  ]
}